[
  {
    "date": "2025-04-04",
    "raceNo": 1,
    "venue": "İzmir",
    "distance": 1900,
    "surface": "Kum",
    "raceClass": "Maiden",
    "horses": [
      {
        "position": 1,
        "no": "11",
        "name": "MADAME SCARLET",
        "jockey": "MERTCAN ÇELİK",
        "trainer": "İBRAHİM HALİL BAYDAN",
        "weight": 56,
        "odds": 2.5,
        "finishTime": "2.05.06",
        "age": 3
      },
      {
        "position": 2,
        "no": "2",
        "name": "KAFKASYA BEYLERİ",
        "jockey": "SİNAN ÖZEN",
        "trainer": "BAŞOL ÖZGÜR",
        "weight": 60,
        "odds": 5.5,
        "finishTime": "2.06.43",
        "age": 3
      },
      {
        "position": 3,
        "no": "1",
        "name": "THE SIGNATURE",
        "jockey": "MEHMET KAYA",
        "trainer": "NİHAN DÖNMEZ",
        "weight": 61,
        "odds": 3.1,
        "finishTime": "2.06.62",
        "age": 3
      },
      {
        "position": 4,
        "no": "8",
        "name": "ALWAYS A REASON",
        "jockey": "ÖMER FARUK ÖZEN",
        "trainer": "ÜLKÜ AYBOĞA",
        "weight": 52,
        "odds": 44.85,
        "finishTime": "2.06.88",
        "age": 3
      },
      {
        "position": 5,
        "no": "6",
        "name": "MASTER SHİFU",
        "jockey": "MURAT KEÇECİ",
        "trainer": "FAHRETTİN CEYLAN",
        "weight": 54,
        "odds": 36.8,
        "finishTime": "2.07.30",
        "age": 3
      },
      {
        "position": 6,
        "no": "4",
        "name": "DOĞU ASLANI",
        "jockey": "ALAATTİN KÜRÜNDÜK",
        "trainer": "ÜLKÜ AYBOĞA",
        "weight": 58,
        "odds": 11,
        "finishTime": "2.07.65",
        "age": 3
      },
      {
        "position": 7,
        "no": "3",
        "name": "ASTRO LORD",
        "jockey": "BEKİR MERT MIRIK",
        "trainer": "MEHMET YAPAROĞLU",
        "weight": 58,
        "odds": 17.6,
        "finishTime": "2.12.65",
        "age": 3
      },
      {
        "position": 8,
        "no": "7",
        "name": "ROCKET FIRE",
        "jockey": "MUSTAFA ÇİÇEK",
        "trainer": "MELİH MEHMET İNAL",
        "weight": 58,
        "odds": 11.7,
        "finishTime": "2.12.90",
        "age": 3
      },
      {
        "position": 9,
        "no": "5",
        "name": "EGELİ ATLAS",
        "jockey": "ERHAN AKTUĞ",
        "trainer": "MELİH TEZEL",
        "weight": 58,
        "odds": 22.6,
        "finishTime": "2.13.67",
        "age": 3
      },
      {
        "position": 10,
        "no": "12",
        "name": "MISSION IMPOSSIBLE",
        "jockey": "MUHAMMED MİR BİLGİN",
        "trainer": "TAYFUN VATANSEVER",
        "weight": 56,
        "odds": 13.7,
        "finishTime": "2.14.38",
        "age": 3
      },
      {
        "position": 11,
        "no": "10",
        "name": "HAYAL TAY",
        "jockey": "İBRAHİM SEFA SÖĞÜT",
        "trainer": "SADIK İŞLETİR",
        "weight": 53,
        "odds": 31.1,
        "finishTime": "2.15.05",
        "age": 3
      }
    ]
  },
  {
    "date": "2025-04-04",
    "raceNo": 2,
    "venue": "İzmir",
    "distance": 1600,
    "surface": "Kum",
    "raceClass": "SATIŞ 1/DHÖW",
    "horses": [
      {
        "position": 1,
        "no": "4",
        "name": "HOLİGAN",
        "jockey": "MUSTAFA ÇİÇEK",
        "trainer": "SEMİ YUDUM",
        "weight": 56.5,
        "odds": 2.15,
        "finishTime": "1.51.92",
        "age": 9
      },
      {
        "position": 2,
        "no": "1",
        "name": "SULTANYEL",
        "jockey": "MUHAMMED MİR BİLGİN",
        "trainer": "MELİH TEZEL",
        "weight": 58.5,
        "odds": 2.7,
        "finishTime": "1.52.04",
        "age": 6
      },
      {
        "position": 3,
        "no": "3",
        "name": "BAŞPARMAK",
        "jockey": "MEHMET KAYA",
        "trainer": "EMİR CİHAN BAYDAN",
        "weight": 56.5,
        "odds": 7.3,
        "finishTime": "1.52.63",
        "age": 8
      },
      {
        "position": 4,
        "no": "2",
        "name": "YOLKIRAN",
        "jockey": "İBRAHİM SEFA SÖĞÜT",
        "trainer": "HALİL ERSİN UYSAL",
        "weight": 58.5,
        "odds": 5.25,
        "finishTime": "1.52.84",
        "age": 10
      },
      {
        "position": 5,
        "no": "5",
        "name": "SARIYERLİ",
        "jockey": "GÖRKEM ÖZÇELİK",
        "trainer": "HALİL ERSİN UYSAL",
        "weight": 55.5,
        "odds": 7.4,
        "finishTime": "1.53.60",
        "age": 7
      },
      {
        "position": 6,
        "no": "7",
        "name": "KRAL HAKAN",
        "jockey": "EREN DURSUN ÖKTEN",
        "trainer": "TEKİN BİRİCİK",
        "weight": 51.5,
        "odds": 38.9,
        "finishTime": "1.57.01",
        "age": 5
      },
      {
        "position": 7,
        "no": "6",
        "name": "YEŞİLOVALI",
        "jockey": "HALİT GÖKÇE",
        "trainer": "MURAT TÜRKOĞLU",
        "weight": 54,
        "odds": 49.7,
        "finishTime": "1.57.48",
        "age": 4
      }
    ]
  },
  {
    "date": "2025-04-04",
    "raceNo": 3,
    "venue": "İzmir",
    "distance": 1900,
    "surface": "Kum",
    "raceClass": "ŞARTLI 3/DHÖW/Dişi",
    "horses": [
      {
        "position": 1,
        "no": "6",
        "name": "SELCAN HATUN",
        "jockey": "ALAATTİN KÜRÜNDÜK",
        "trainer": "CENGİZ TEKİN KÖSE",
        "weight": 57.5,
        "odds": 4.5,
        "finishTime": "2.16.14",
        "age": 6
      },
      {
        "position": 2,
        "no": "3",
        "name": "HAVZALI",
        "jockey": "OĞUZ EREN",
        "trainer": "ÜLKÜ AYBOĞA",
        "weight": 58.5,
        "odds": 4,
        "finishTime": "2.16.48",
        "age": 8
      },
      {
        "position": 3,
        "no": "12",
        "name": "SİNSİNATEŞİ",
        "jockey": "MUSTAFA ÇİÇEK",
        "trainer": "TUNCAY ATEŞ",
        "weight": 57.5,
        "odds": 11.2,
        "finishTime": "2.17.19",
        "age": 5
      },
      {
        "position": 4,
        "no": "7",
        "name": "SUFLE",
        "jockey": "CEM ALTUN",
        "trainer": "MEHMET YAPAROĞLU",
        "weight": 54.5,
        "odds": 6.85,
        "finishTime": "2.17.26",
        "age": 7
      },
      {
        "position": 5,
        "no": "13",
        "name": "SAMSAT",
        "jockey": "HALİL YOLAÇICI",
        "trainer": "NURETTİN GÖNÜLTAŞ",
        "weight": 57.5,
        "odds": 16.05,
        "finishTime": "2.17.29",
        "age": 5
      },
      {
        "position": 6,
        "no": "2",
        "name": "CANCAZIM",
        "jockey": "ERHAN AKTUĞ",
        "trainer": "BAYRAM KOCAKAYA",
        "weight": 57.5,
        "odds": 26.1,
        "finishTime": "2.17.74",
        "age": 5
      },
      {
        "position": 7,
        "no": "8",
        "name": "RÜZGARTEPESİ",
        "jockey": "BEKİR MERT MIRIK",
        "trainer": "TUNCAY ATEŞ",
        "weight": 57.5,
        "odds": 20.9,
        "finishTime": "2.18.00",
        "age": 5
      },
      {
        "position": 8,
        "no": "9",
        "name": "ADEN PERİSİ",
        "jockey": "MUHAMMED MİR BİLGİN",
        "trainer": "MUHAMMED UĞUR TURAN",
        "weight": 57.5,
        "odds": 6.15,
        "finishTime": "2.18.04",
        "age": 6
      },
      {
        "position": 9,
        "no": "10",
        "name": "ÖZGÜR ODİN",
        "jockey": "MERT UYAR",
        "trainer": "CENGİZ TEKİN KÖSE",
        "weight": 51,
        "odds": 4.5,
        "finishTime": "2.18.22",
        "age": 4
      },
      {
        "position": 10,
        "no": "4",
        "name": "HUMAY KIZIM",
        "jockey": "MEHMET KAYA",
        "trainer": "TEKİN DURAN",
        "weight": 57.5,
        "odds": 4.65,
        "finishTime": "2.20.09",
        "age": 5
      },
      {
        "position": 11,
        "no": "11",
        "name": "ÖZÜMCAN",
        "jockey": "İBRAHİM SEFA SÖĞÜT",
        "trainer": "ÜLKÜ AYBOĞA",
        "weight": 54.5,
        "odds": 54.2,
        "finishTime": "2.20.18",
        "age": 8
      },
      {
        "position": 12,
        "no": "14",
        "name": "ALLER GÜLÜ",
        "jockey": "ONUR ATMACA",
        "trainer": "AHMET ÖZGEN",
        "weight": 57.5,
        "odds": 38.5,
        "finishTime": "2.24.01",
        "age": 5
      },
      {
        "position": 13,
        "no": "1",
        "name": "ŞİNTAY",
        "jockey": "ALPEREN OLUK",
        "trainer": "MELEK ÖZGÜL",
        "weight": 57.5,
        "odds": 40.25,
        "finishTime": "2.39.68",
        "age": 9
      },
      {
        "position": 14,
        "no": "5",
        "name": "KOŞAN NUR",
        "jockey": "GÖRKEM ÖZÇELİK",
        "trainer": "İBRAHİM HALİL BAYDAN",
        "weight": 57.5,
        "odds": 27.1,
        "finishTime": "2.44.50",
        "age": 5
      }
    ]
  },
  {
    "date": "2025-04-04",
    "raceNo": 4,
    "venue": "İzmir",
    "distance": 1900,
    "surface": "Kum",
    "raceClass": "Maiden",
    "horses": [
      {
        "position": 1,
        "no": "6",
        "name": "UZUN ALİ",
        "jockey": "MUHAMMED MİR BİLGİN",
        "trainer": "HIDIR DURMUŞ",
        "weight": 58,
        "odds": 1.5,
        "finishTime": "2.07.06",
        "age": 3
      },
      {
        "position": 2,
        "no": "1",
        "name": "BIG FATHER KAYRA",
        "jockey": "MUHARREM OK",
        "trainer": "TAYFUN VATANSEVER",
        "weight": 55,
        "odds": 37.85,
        "finishTime": "2.07.35",
        "age": 3
      },
      {
        "position": 3,
        "no": "5",
        "name": "KARAMANIDS",
        "jockey": "GÖKHAN GÖKÇE",
        "trainer": "YASİN POLAT",
        "weight": 58,
        "odds": 11.5,
        "finishTime": "2.07.58",
        "age": 3
      },
      {
        "position": 4,
        "no": "10",
        "name": "SO SECRET",
        "jockey": "MUSTAFA ÇİÇEK",
        "trainer": "ALİCAN ÖKSÜZLER",
        "weight": 56,
        "odds": 5.75,
        "finishTime": "2.07.93",
        "age": 3
      },
      {
        "position": 5,
        "no": "12",
        "name": "VİSTERYA",
        "jockey": "ENES ÜSTÜN",
        "trainer": "TEKİN DURAN",
        "weight": 55,
        "odds": 20.2,
        "finishTime": "2.07.94",
        "age": 3
      },
      {
        "position": 6,
        "no": "7",
        "name": "KITTY PRYDE",
        "jockey": "TUGAY ALICI",
        "trainer": "ZAFER TURĞUL",
        "weight": 56,
        "odds": 9.3,
        "finishTime": "2.08.79",
        "age": 3
      },
      {
        "position": 7,
        "no": "4",
        "name": "HARD BOY",
        "jockey": "BEKİR MERT MIRIK",
        "trainer": "SEYHAN DEMİR",
        "weight": 58,
        "odds": 10.2,
        "finishTime": "2.08.87",
        "age": 3
      },
      {
        "position": 8,
        "no": "11",
        "name": "TICKET TO PARADISE",
        "jockey": "ERHAN AKTUĞ",
        "trainer": "BARIŞ TOPCU",
        "weight": 56,
        "odds": 15.5,
        "finishTime": "2.09.46",
        "age": 3
      },
      {
        "position": 9,
        "no": "2",
        "name": "GANGPLANK",
        "jockey": "ALAATTİN KÜRÜNDÜK",
        "trainer": "NURETTİN GÖNÜLTAŞ",
        "weight": 58,
        "odds": 27.8,
        "finishTime": "2.09.81",
        "age": 3
      },
      {
        "position": 10,
        "no": "8",
        "name": "QUEEN OF MIRANDA",
        "jockey": "İLKER SOYAD",
        "trainer": "MURAT AKSOY",
        "weight": 56,
        "odds": 85.95,
        "finishTime": "2.10.84",
        "age": 3
      },
      {
        "position": 11,
        "no": "9",
        "name": "SIZMANA",
        "jockey": "ONUR ATMACA",
        "trainer": "TUNCAY ATEŞ",
        "weight": 56,
        "odds": 55.15,
        "finishTime": "2.15.53",
        "age": 3
      }
    ]
  },
  {
    "date": "2025-04-04",
    "raceNo": 5,
    "venue": "İzmir",
    "distance": 1900,
    "surface": "Kum",
    "raceClass": "KV-6/DHÖW",
    "horses": [
      {
        "position": 1,
        "no": "1",
        "name": "UFKUN ÖTESİ",
        "jockey": "MEHMET KAYA",
        "trainer": "CENGİZ AYDOĞAN",
        "weight": 61,
        "odds": 2,
        "finishTime": "2.15.21",
        "age": 4
      },
      {
        "position": 2,
        "no": "4",
        "name": "SAADINSOYU",
        "jockey": "MUHAMMED MİR BİLGİN",
        "trainer": "İBRAHİM HALİL BAYDAN",
        "weight": 55,
        "odds": 6.8,
        "finishTime": "2.15.52",
        "age": 4
      },
      {
        "position": 3,
        "no": "6",
        "name": "DEREBEYİ",
        "jockey": "ERHAN AKTUĞ",
        "trainer": "EMRAH AYHAN",
        "weight": 54,
        "odds": 9.8,
        "finishTime": "2.17.26",
        "age": 4
      },
      {
        "position": 4,
        "no": "5",
        "name": "AKAYDIN",
        "jockey": "ALPEREN OLUK",
        "trainer": "MELİH TEZEL",
        "weight": 54,
        "odds": 10.05,
        "finishTime": "2.17.35",
        "age": 4
      },
      {
        "position": 5,
        "no": "11",
        "name": "SOĞUK KUYU",
        "jockey": "BEKİR MERT MIRIK",
        "trainer": "EMİR CİHAN BAYDAN",
        "weight": 54,
        "odds": 6.5,
        "finishTime": "2.17.39",
        "age": 4
      },
      {
        "position": 6,
        "no": "13",
        "name": "BY VOLKAN",
        "jockey": "İLKER SOYAD",
        "trainer": "MUSTAFA KAYA",
        "weight": 54,
        "odds": 40.1,
        "finishTime": "2.18.14",
        "age": 4
      },
      {
        "position": 7,
        "no": "9",
        "name": "TÜRKAN HANIM",
        "jockey": "GÖRKEM ÖZÇELİK",
        "trainer": "İBRAHİM HALİL BAYDAN",
        "weight": 54,
        "odds": 11.95,
        "finishTime": "2.18.25",
        "age": 4
      },
      {
        "position": 8,
        "no": "3",
        "name": "ŞİMŞEK ALMHIMID",
        "jockey": "MURAT KEÇECİ",
        "trainer": "MELİH TEZEL",
        "weight": 56,
        "odds": 10.05,
        "finishTime": "2.19.27",
        "age": 4
      },
      {
        "position": 9,
        "no": "7",
        "name": "İKİGAİ",
        "jockey": "İBRAHİM SEFA SÖĞÜT",
        "trainer": "MELEK ÖZGÜL",
        "weight": 54,
        "odds": 8,
        "finishTime": "2.19.34",
        "age": 4
      },
      {
        "position": 10,
        "no": "10",
        "name": "TEPEBAŞI",
        "jockey": "TUGAY ALICI",
        "trainer": "ÜLKÜ AYBOĞA",
        "weight": 55,
        "odds": 20.6,
        "finishTime": "2.20.31",
        "age": 4
      },
      {
        "position": 11,
        "no": "2",
        "name": "EGE ASLANI",
        "jockey": "ONUR ATMACA",
        "trainer": "MELİH TEZEL",
        "weight": 56,
        "odds": 40.6,
        "finishTime": "2.20.56",
        "age": 4
      },
      {
        "position": 12,
        "no": "12",
        "name": "KOÇERHAN",
        "jockey": "CEM ALTUN",
        "trainer": "ÜLKÜ AYBOĞA",
        "weight": 54,
        "odds": 51.15,
        "finishTime": "2.23.45",
        "age": 4
      },
      {
        "position": 13,
        "no": "14",
        "name": "ZEYNEP HANDE",
        "jockey": "ENES ÜSTÜN",
        "trainer": "REŞİT KARATAŞ",
        "weight": 54,
        "odds": 105.45,
        "finishTime": "2.26.76",
        "age": 4
      }
    ]
  },
  {
    "date": "2025-04-04",
    "raceNo": 6,
    "venue": "İzmir",
    "distance": 1400,
    "surface": "Kum",
    "raceClass": "KV-7/Dişi",
    "horses": [
      {
        "position": 1,
        "no": "1",
        "name": "SWEET SACRIFICE",
        "jockey": "ÖZCAN YILDIRIM",
        "trainer": "ALİCAN ÖKSÜZLER",
        "weight": 58,
        "odds": 2.65,
        "finishTime": "1.26.44",
        "age": 4
      },
      {
        "position": 2,
        "no": "2",
        "name": "MON COEUR",
        "jockey": "MUSTAFA ÇİÇEK",
        "trainer": "ÖMER ALAÇAM",
        "weight": 56,
        "odds": 5.05,
        "finishTime": "1.26.47",
        "age": 4
      },
      {
        "position": 3,
        "no": "4",
        "name": "LAVENDER",
        "jockey": "VEDAT ABİŞ",
        "trainer": "MEHMET ALTUNBAŞ",
        "weight": 55,
        "odds": 2,
        "finishTime": "1.26.61",
        "age": 5
      },
      {
        "position": 4,
        "no": "",
        "name": "HIMALAYAN(3) (USA)",
        "jockey": "MUHAMMED MİR BİLGİN",
        "trainer": "ADİL OCAK",
        "weight": 55,
        "odds": 5.45,
        "finishTime": "1.27.20",
        "age": 4
      },
      {
        "position": 5,
        "no": "5",
        "name": "THUNDER JEST",
        "jockey": "GÖRKEM ÖZÇELİK",
        "trainer": "YAKUP AKKILIÇ",
        "weight": 55,
        "odds": 18.65,
        "finishTime": "1.27.63",
        "age": 6
      },
      {
        "position": 6,
        "no": "6",
        "name": "CANIM SELİN",
        "jockey": "BEKİR MERT MIRIK",
        "trainer": "MELİH TEZEL",
        "weight": 55,
        "odds": 27.15,
        "finishTime": "1.27.82",
        "age": 4
      }
    ]
  },
  {
    "date": "2025-04-04",
    "raceNo": 7,
    "venue": "İzmir",
    "distance": 1900,
    "surface": "Kum",
    "raceClass": "KV-6",
    "horses": [
      {
        "position": 1,
        "no": "1",
        "name": "DROWZEE",
        "jockey": "VEDAT ABİŞ",
        "trainer": "TAYFUN VATANSEVER",
        "weight": 58,
        "odds": 1.2,
        "finishTime": "2.02.86",
        "age": 3
      },
      {
        "position": 2,
        "no": "4",
        "name": "MONEY HUNTER",
        "jockey": "GÖRKEM ÖZÇELİK",
        "trainer": "EMRAH AYHAN",
        "weight": 58,
        "odds": 5.8,
        "finishTime": "2.02.99",
        "age": 3
      },
      {
        "position": 3,
        "no": "7",
        "name": "RUNNER",
        "jockey": "ERHAN AKTUĞ",
        "trainer": "YAŞAR ARSLANCA",
        "weight": 52,
        "odds": 26.15,
        "finishTime": "2.04.10",
        "age": 3
      },
      {
        "position": 4,
        "no": "2",
        "name": "ERBAALI SADİ",
        "jockey": "MUHAMMED MİR BİLGİN",
        "trainer": "TAYFUN VATANSEVER",
        "weight": 58,
        "odds": 5.25,
        "finishTime": "2.04.48",
        "age": 3
      },
      {
        "position": 5,
        "no": "5",
        "name": "ALL OF DREAMS",
        "jockey": "TUGAY ALICI",
        "trainer": "EMRAH AYHAN",
        "weight": 55,
        "odds": 40.3,
        "finishTime": "2.04.81",
        "age": 3
      },
      {
        "position": 6,
        "no": "3",
        "name": "LITTLE JOE",
        "jockey": "MEHMET KAYA",
        "trainer": "VELAT KARAKUŞ",
        "weight": 58,
        "odds": 9.75,
        "finishTime": "2.05.03",
        "age": 3
      }
    ]
  },
  {
    "date": "2025-04-04",
    "raceNo": 8,
    "venue": "İzmir",
    "distance": 1900,
    "surface": "Kum",
    "raceClass": "Maiden",
    "horses": [
      {
        "position": 1,
        "no": "3",
        "name": "ÇİFTÇİ",
        "jockey": "ERHAN AKTUĞ",
        "trainer": "MEHMET TAMER",
        "weight": 58,
        "odds": 22.5,
        "finishTime": "2.05.15",
        "age": 3
      },
      {
        "position": 2,
        "no": "13",
        "name": "WINGS OF FREEDOM",
        "jockey": "GÖRKEM ÖZÇELİK",
        "trainer": "ZAFER TURĞUL",
        "weight": 56,
        "odds": 17.65,
        "finishTime": "2.05.67",
        "age": 3
      },
      {
        "position": 3,
        "no": "9",
        "name": "BAYS",
        "jockey": "CEM ALTUN",
        "trainer": "TEKİN DURAN",
        "weight": 53,
        "odds": 49.35,
        "finishTime": "2.06.49",
        "age": 3
      },
      {
        "position": 4,
        "no": "4",
        "name": "DARK RIDER",
        "jockey": "İBRAHİM SEFA SÖĞÜT",
        "trainer": "MUTULLAH KAYA",
        "weight": 55,
        "odds": 9.9,
        "finishTime": "2.06.52",
        "age": 3
      },
      {
        "position": 5,
        "no": "1",
        "name": "BLACK BREEZE",
        "jockey": "SİNAN ÖZEN",
        "trainer": "EMİR CİHAN BAYDAN",
        "weight": 61,
        "odds": 5.2,
        "finishTime": "2.06.65",
        "age": 3
      },
      {
        "position": 6,
        "no": "2",
        "name": "DARK SOUL",
        "jockey": "MUHAMMED MİR BİLGİN",
        "trainer": "MEHMET GÜDÜCÜ",
        "weight": 61,
        "odds": 8.3,
        "finishTime": "2.08.36",
        "age": 3
      },
      {
        "position": 7,
        "no": "11",
        "name": "SICAK",
        "jockey": "ALPEREN OLUK",
        "trainer": "MEHMET YAPAROĞLU",
        "weight": 54,
        "odds": 20.7,
        "finishTime": "2.09.68",
        "age": 3
      },
      {
        "position": 8,
        "no": "7",
        "name": "THUNDER HORSE",
        "jockey": "MERTCAN ÇELİK",
        "trainer": "İBRAHİM HALİL BAYDAN",
        "weight": 58,
        "odds": 7,
        "finishTime": "2.10.28",
        "age": 3
      },
      {
        "position": 9,
        "no": "8",
        "name": "ANNEM GÜLDANE",
        "jockey": "MUHARREM OK",
        "trainer": "ANIL KARABIYIK",
        "weight": 53,
        "odds": 47.2,
        "finishTime": "2.15.60",
        "age": 3
      },
      {
        "position": 10,
        "no": "12",
        "name": "WEDNESDAY",
        "jockey": "ONUR ATMACA",
        "trainer": "MELİH TEZEL",
        "weight": 56,
        "odds": 48.8,
        "finishTime": "2.22.76",
        "age": 3
      }
    ]
  },
  {
    "date": "2025-04-04",
    "raceNo": 9,
    "venue": "İzmir",
    "distance": 1200,
    "surface": "Kum",
    "raceClass": "Handikap 16 /H1",
    "horses": [
      {
        "position": 1,
        "no": "6",
        "name": "MANCUNIAN BEDİİ",
        "jockey": "MURAT KEÇECİ",
        "trainer": "GÖKHAN ER",
        "weight": 52,
        "odds": 13.95,
        "finishTime": "1.13.58",
        "age": 4
      },
      {
        "position": 2,
        "no": "4",
        "name": "BATTLECAT",
        "jockey": "MUHAMMED MİR BİLGİN",
        "trainer": "TAYFUN VATANSEVER",
        "weight": 54.5,
        "odds": 7.2,
        "finishTime": "1.13.80",
        "age": 4
      },
      {
        "position": 3,
        "no": "5",
        "name": "NAZGAR",
        "jockey": "MUSTAFA ÇİÇEK",
        "trainer": "ALİDEVRAN BEKTAŞ",
        "weight": 54.5,
        "odds": 5.6,
        "finishTime": "1.14.22",
        "age": 4
      },
      {
        "position": 4,
        "no": "1",
        "name": "APOLOGIZE",
        "jockey": "MEHMET KAYA",
        "trainer": "ÜLKÜ AYBOĞA",
        "weight": 63,
        "odds": 2.5,
        "finishTime": "1.14.44",
        "age": 4
      },
      {
        "position": 5,
        "no": "2",
        "name": "DR AZİZ",
        "jockey": "CEM ALTUN",
        "trainer": "ALİCAN ÖKSÜZLER",
        "weight": 60.5,
        "odds": 20.55,
        "finishTime": "1.14.50",
        "age": 5
      },
      {
        "position": 6,
        "no": "13",
        "name": "BATMANBEYİ",
        "jockey": "ONUR ATMACA",
        "trainer": "ÜMÜT BULUT",
        "weight": 50,
        "odds": 20.75,
        "finishTime": "1.15.22",
        "age": 4
      },
      {
        "position": 7,
        "no": "11",
        "name": "WHISTLE ARROW",
        "jockey": "MERT UYAR",
        "trainer": "BİROL ŞENGEL",
        "weight": 50,
        "odds": 7.45,
        "finishTime": "1.15.40",
        "age": 4
      },
      {
        "position": 8,
        "no": "10",
        "name": "OLORFO",
        "jockey": "HALİT GÖKÇE",
        "trainer": "TEKİN DURAN",
        "weight": 50,
        "odds": 18.2,
        "finishTime": "1.15.46",
        "age": 4
      },
      {
        "position": 9,
        "no": "14",
        "name": "ROTASIZ KAPTAN",
        "jockey": "HALİL YOLAÇICI",
        "trainer": "ÜLKÜ AYBOĞA",
        "weight": 50,
        "odds": 7.3,
        "finishTime": "1.15.99",
        "age": 5
      },
      {
        "position": 10,
        "no": "7",
        "name": "BEULIEU",
        "jockey": "ALAATTİN KÜRÜNDÜK",
        "trainer": "MELİH TEZEL",
        "weight": 52.5,
        "odds": 33.65,
        "finishTime": "1.16.07",
        "age": 5
      },
      {
        "position": 11,
        "no": "3",
        "name": "OĞLUM MUSTAFA",
        "jockey": "BEKİR MERT MIRIK",
        "trainer": "ALİCAN ÖKSÜZLER",
        "weight": 55,
        "odds": 14.6,
        "finishTime": "1.16.67",
        "age": 4
      },
      {
        "position": 12,
        "no": "8",
        "name": "HOEYON",
        "jockey": "İBRAHİM SEFA SÖĞÜT",
        "trainer": "FAHRETTİN CEYLAN",
        "weight": 51.5,
        "odds": 32.85,
        "finishTime": "1.17.32",
        "age": 5
      }
    ]
  },
  {
    "date": "2025-04-04",
    "raceNo": 1,
    "venue": "Antalya",
    "distance": 1300,
    "surface": "Kum",
    "raceClass": "Maiden/DHÖW",
    "horses": [
      {
        "position": 1,
        "no": "3",
        "name": "ROL MODEL",
        "jockey": "AYHAN KURŞUN",
        "trainer": "ALİ RIZA YILDIZ",
        "weight": 60,
        "odds": 1.15,
        "finishTime": "1.31.17",
        "age": 4
      },
      {
        "position": 2,
        "no": "4",
        "name": "CÜREKLİCAŞ",
        "jockey": "GÖKHAN YILDIZ",
        "trainer": "AYCAN POLAT",
        "weight": 58,
        "odds": 33.3,
        "finishTime": "1.32.01",
        "age": 4
      },
      {
        "position": 3,
        "no": "2",
        "name": "ESAT",
        "jockey": "AHMET ÇELİK",
        "trainer": "AHMET MANTAŞ",
        "weight": 60,
        "odds": 6.55,
        "finishTime": "1.32.69",
        "age": 4
      },
      {
        "position": 4,
        "no": "8",
        "name": "YAMAN GÜZELİ",
        "jockey": "HALİL POLAT",
        "trainer": "ADNAN POLAT",
        "weight": 56,
        "odds": 11.4,
        "finishTime": "1.32.72",
        "age": 4
      },
      {
        "position": 5,
        "no": "1",
        "name": "ERTAY",
        "jockey": "ERCAN ÇANKAYA",
        "trainer": "SİNAN YANMAZ",
        "weight": 60,
        "odds": 31.3,
        "finishTime": "1.34.58",
        "age": 4
      },
      {
        "position": 6,
        "no": "7",
        "name": "ŞAHSİNEM",
        "jockey": "HALEF KATI",
        "trainer": "SİBEL AKCI",
        "weight": 56,
        "odds": 12.7,
        "finishTime": "1.36.69",
        "age": 4
      },
      {
        "position": 7,
        "no": "5",
        "name": "ALTINSAÇ",
        "jockey": "MEHMET SALİH ÇELİK",
        "trainer": "MURAT TEKPETEK",
        "weight": 58,
        "odds": 12.45,
        "finishTime": "1.36.80",
        "age": 4
      },
      {
        "position": 8,
        "no": "6",
        "name": "ALIŞILAGELMİŞ",
        "jockey": "ROBİN BORAN DÜNDAR",
        "trainer": "DENİZ ALTIN",
        "weight": 52,
        "odds": 52.85,
        "finishTime": "1.40.78",
        "age": 4
      }
    ]
  },
  {
    "date": "2025-04-04",
    "raceNo": 2,
    "venue": "Antalya",
    "distance": 1400,
    "surface": "Sentetik",
    "raceClass": "Handikap 17 /H1",
    "horses": [
      {
        "position": 1,
        "no": "2",
        "name": "MAKUL",
        "jockey": "SALİH ÇELİK",
        "trainer": "HÜSEYİN ÇALIŞKAN",
        "weight": 58.5,
        "odds": 2.1,
        "finishTime": "1.24.70",
        "age": 4
      },
      {
        "position": 2,
        "no": "6",
        "name": "ROCKET FUEL",
        "jockey": "ADEM ASLAN",
        "trainer": "ALİ RIZA ÇAKAR",
        "weight": 52.5,
        "odds": 11.95,
        "finishTime": "1.24.74",
        "age": 5
      },
      {
        "position": 3,
        "no": "3",
        "name": "EL RIO",
        "jockey": "FURKAN ÇETİN",
        "trainer": "OZAN BULUT",
        "weight": 58.5,
        "odds": 9.3,
        "finishTime": "1.24.75",
        "age": 4
      },
      {
        "position": 4,
        "no": "1",
        "name": "OPPENHEIMER",
        "jockey": "AHMET ÇELİK",
        "trainer": "MURAT AYDOĞDİ",
        "weight": 63,
        "odds": 2.25,
        "finishTime": "1.25.04",
        "age": 4
      },
      {
        "position": 5,
        "no": "4",
        "name": "KATHERİNA",
        "jockey": "ERHAN YAVUZ",
        "trainer": "MERT KORKMAZ",
        "weight": 58.5,
        "odds": 6.3,
        "finishTime": "1.25.08",
        "age": 6
      },
      {
        "position": 6,
        "no": "7",
        "name": "MEŞHUR SAMURAİ",
        "jockey": "SERCAN TIRPAN",
        "trainer": "ADNAN POLAT",
        "weight": 50,
        "odds": 25.1,
        "finishTime": "1.25.09",
        "age": 5
      },
      {
        "position": 7,
        "no": "5",
        "name": "UYGAR BEY",
        "jockey": "HALEF KATI",
        "trainer": "SÜLEYMAN ASLAN",
        "weight": 58,
        "odds": 30.65,
        "finishTime": "1.27.50",
        "age": 5
      }
    ]
  },
  {
    "date": "2025-04-04",
    "raceNo": 3,
    "venue": "Antalya",
    "distance": 2000,
    "surface": "Sentetik",
    "raceClass": "Handikap 15 /H2",
    "horses": [
      {
        "position": 1,
        "no": "6",
        "name": "TREASURE ISLAND",
        "jockey": "MÜSLÜM ÇELİK",
        "trainer": "İBRAHİM TEMEL",
        "weight": 55,
        "odds": 4.65,
        "finishTime": "2.05.98",
        "age": 3
      },
      {
        "position": 2,
        "no": "5",
        "name": "QUEEN OF MY HEART",
        "jockey": "AYHAN KURŞUN",
        "trainer": "BATUHAN TURGUL",
        "weight": 57.5,
        "odds": 6.05,
        "finishTime": "2.06.59",
        "age": 3
      },
      {
        "position": 3,
        "no": "4",
        "name": "RUSCUK",
        "jockey": "SALİH ÇELİK",
        "trainer": "HÜSEYİN ÇALIŞKAN",
        "weight": 55.5,
        "odds": 9.75,
        "finishTime": "2.06.60",
        "age": 3
      },
      {
        "position": 4,
        "no": "2",
        "name": "LOST IN PARADISE",
        "jockey": "UĞUR TEMUR",
        "trainer": "MURAT TEKPETEK",
        "weight": 59,
        "odds": 21.15,
        "finishTime": "2.06.86",
        "age": 3
      },
      {
        "position": 5,
        "no": "8",
        "name": "FINA LUNA",
        "jockey": "ADEM ASLAN",
        "trainer": "VEYSEL AKBAŞ",
        "weight": 53.5,
        "odds": 18.15,
        "finishTime": "2.06.96",
        "age": 3
      },
      {
        "position": 6,
        "no": "3",
        "name": "ZEMZEMANA",
        "jockey": "MEHMET SALİH ÇELİK",
        "trainer": "HÜSEYİN KARATAŞ",
        "weight": 59,
        "odds": 3.05,
        "finishTime": "2.07.18",
        "age": 3
      },
      {
        "position": 7,
        "no": "7",
        "name": "ERKOÇUM",
        "jockey": "AHMET ÇELİK",
        "trainer": "TOLGA SÜSLÜ",
        "weight": 54,
        "odds": 4.2,
        "finishTime": "2.07.28",
        "age": 3
      },
      {
        "position": 8,
        "no": "9",
        "name": "LAST STROM",
        "jockey": "SERCAN TIRPAN",
        "trainer": "KENAN KORKMAZ",
        "weight": 53.5,
        "odds": 19.05,
        "finishTime": "2.07.43",
        "age": 3
      },
      {
        "position": 9,
        "no": "1",
        "name": "MEGA LOVE",
        "jockey": "FURKAN ÇETİN",
        "trainer": "ÖMER YILDIRIM",
        "weight": 58.5,
        "odds": 10.3,
        "finishTime": "2.09.18",
        "age": 3
      },
      {
        "position": 10,
        "no": "10",
        "name": "SAHA YAKUT",
        "jockey": "BURAK AKÇAY",
        "trainer": "HAMZA KAYA",
        "weight": 52.5,
        "odds": 27.1,
        "finishTime": "2.10.79",
        "age": 3
      }
    ]
  },
  {
    "date": "2025-04-04",
    "raceNo": 4,
    "venue": "Antalya",
    "distance": 1200,
    "surface": "Kum",
    "raceClass": "KV-7/DHÖW/Dişi",
    "horses": [
      {
        "position": 1,
        "no": "8",
        "name": "UMUDUMUZ",
        "jockey": "UĞUR TEMUR",
        "trainer": "ÖMER ALTIN",
        "weight": 54,
        "odds": 2.05,
        "finishTime": "1.21.82",
        "age": 4
      },
      {
        "position": 2,
        "no": "2",
        "name": "ŞEKLİ",
        "jockey": "MEHMET AKYAVUZ",
        "trainer": "AHMET KORKMAZ",
        "weight": 56,
        "odds": 4.55,
        "finishTime": "1.22.00",
        "age": 4
      },
      {
        "position": 3,
        "no": "4",
        "name": "REYHAN GELİN",
        "jockey": "AHMET ÇELİK",
        "trainer": "RESUL KAYA",
        "weight": 55,
        "odds": 4.5,
        "finishTime": "1.22.57",
        "age": 4
      },
      {
        "position": 4,
        "no": "6",
        "name": "CEVİZ AĞACI",
        "jockey": "SERCAN TIRPAN",
        "trainer": "ULVİ YOĞURTCU",
        "weight": 54,
        "odds": 34.45,
        "finishTime": "1.23.42",
        "age": 4
      },
      {
        "position": 5,
        "no": "1",
        "name": "EFLİN ESLEM",
        "jockey": "MÜSLÜM ÇELİK",
        "trainer": "YUSUF UÇAR",
        "weight": 58,
        "odds": 4.05,
        "finishTime": "1.23.49",
        "age": 4
      },
      {
        "position": 6,
        "no": "7",
        "name": "LAVİN FIRTINASI",
        "jockey": "ERCAN ÇANKAYA",
        "trainer": "ADNAN POLAT",
        "weight": 55,
        "odds": 13.75,
        "finishTime": "1.25.03",
        "age": 4
      }
    ]
  },
  {
    "date": "2025-04-04",
    "raceNo": 5,
    "venue": "Antalya",
    "distance": 1400,
    "surface": "Kum",
    "raceClass": "KV-6",
    "horses": [
      {
        "position": 1,
        "no": "1",
        "name": "I HAVE A DREAM",
        "jockey": "ERCAN ÇANKAYA",
        "trainer": "ADNAN POLAT",
        "weight": 59,
        "odds": 1.95,
        "finishTime": "1.27.44",
        "age": 3
      },
      {
        "position": 2,
        "no": "2",
        "name": "BAY TOPÇU",
        "jockey": "UĞUR TEMUR",
        "trainer": "HAMZA KAYA",
        "weight": 58,
        "odds": 5.95,
        "finishTime": "1.27.49",
        "age": 3
      },
      {
        "position": 3,
        "no": "6",
        "name": "BUCALI BERAT",
        "jockey": "ERHAN YAVUZ",
        "trainer": "SEDA UYSAL",
        "weight": 55,
        "odds": 15.8,
        "finishTime": "1.27.83",
        "age": 3
      },
      {
        "position": 4,
        "no": "5",
        "name": "MAVİ TOPAZ",
        "jockey": "MÜSLÜM ÇELİK",
        "trainer": "MÜSLÜM ÖRTÜNÇ",
        "weight": 56,
        "odds": 5.1,
        "finishTime": "1.27.85",
        "age": 3
      },
      {
        "position": 5,
        "no": "3",
        "name": "EL VERDUGO",
        "jockey": "AHMET ÇELİK",
        "trainer": "CASIM KATI",
        "weight": 58,
        "odds": 2.75,
        "finishTime": "1.28.64",
        "age": 3
      },
      {
        "position": 6,
        "no": "4",
        "name": "BAKIRINOĞLU",
        "jockey": "BURAK AKÇAY",
        "trainer": "HAMZA KAYA",
        "weight": 56,
        "odds": 5.95,
        "finishTime": "1.30.72",
        "age": 3
      },
      {
        "position": 7,
        "no": "8",
        "name": "ROSALİA",
        "jockey": "MEHMET SALİH ÇELİK",
        "trainer": "CASIM KATI",
        "weight": 53,
        "odds": 2.75,
        "finishTime": "1.31.47",
        "age": 3
      }
    ]
  },
  {
    "date": "2025-04-04",
    "raceNo": 6,
    "venue": "Antalya",
    "distance": 2200,
    "surface": "Kum",
    "raceClass": "Handikap 14 /H1",
    "horses": [
      {
        "position": 1,
        "no": "1",
        "name": "HAPPY BOY",
        "jockey": "SALİH ÇELİK",
        "trainer": "BATUHAN TURGUL",
        "weight": 58.5,
        "odds": 2.75,
        "finishTime": "2.25.55",
        "age": 4
      },
      {
        "position": 2,
        "no": "4",
        "name": "CEYHAN SERDARI",
        "jockey": "AHMET ÇELİK",
        "trainer": "TOLGA SÜSLÜ",
        "weight": 59,
        "odds": 1.75,
        "finishTime": "2.26.23",
        "age": 4
      },
      {
        "position": 3,
        "no": "2",
        "name": "RIBANDO",
        "jockey": "FURKAN ÇETİN",
        "trainer": "BATUHAN TURGUL",
        "weight": 61,
        "odds": 13.25,
        "finishTime": "2.28.40",
        "age": 5
      },
      {
        "position": 4,
        "no": "5",
        "name": "GLOWMANE",
        "jockey": "UĞUR TEMUR",
        "trainer": "HAMZA KAYA",
        "weight": 58.5,
        "odds": 5.7,
        "finishTime": "2.28.85",
        "age": 5
      },
      {
        "position": 5,
        "no": "6",
        "name": "NICOLICA",
        "jockey": "ADEM ASLAN",
        "trainer": "CEMİL TURAN",
        "weight": 53,
        "odds": 11.1,
        "finishTime": "2.28.94",
        "age": 4
      },
      {
        "position": 6,
        "no": "3",
        "name": "BABA RÜSTEM",
        "jockey": "HALEF KATI",
        "trainer": "HÜSEYİN KARABULUT",
        "weight": 60.5,
        "odds": 14.8,
        "finishTime": "2.30.91",
        "age": 4
      }
    ]
  },
  {
    "date": "2025-04-04",
    "raceNo": 7,
    "venue": "Antalya",
    "distance": 1300,
    "surface": "Kum",
    "raceClass": "Maiden/DHÖW",
    "horses": [
      {
        "position": 1,
        "no": "4",
        "name": "TOPRAK BEYİ",
        "jockey": "HALEF KATI",
        "trainer": "SERCAN ÇELİKMAN",
        "weight": 58,
        "odds": 1.8,
        "finishTime": "1.31.37",
        "age": 4
      },
      {
        "position": 2,
        "no": "9",
        "name": "SOYLU YARİM",
        "jockey": "İLKER AKIN",
        "trainer": "DENİZ ALTIN",
        "weight": 55,
        "odds": 38.75,
        "finishTime": "1.32.02",
        "age": 4
      },
      {
        "position": 3,
        "no": "1",
        "name": "KINIK BEYİ",
        "jockey": "SADIK ALTAY",
        "trainer": "RESUL KAYA",
        "weight": 62,
        "odds": 5.3,
        "finishTime": "1.32.81",
        "age": 4
      },
      {
        "position": 4,
        "no": "8",
        "name": "SOĞUK SU",
        "jockey": "MEHMET SALİH ÇELİK",
        "trainer": "YUSUF YILDIZ",
        "weight": 56,
        "odds": 7.75,
        "finishTime": "1.32.89",
        "age": 4
      },
      {
        "position": 5,
        "no": "2",
        "name": "EMİRSİN",
        "jockey": "AHMET ÇELİK",
        "trainer": "MERT KORKMAZ",
        "weight": 58,
        "odds": 6.8,
        "finishTime": "1.34.10",
        "age": 4
      },
      {
        "position": 6,
        "no": "6",
        "name": "GÜNERİ",
        "jockey": "BURAK AKÇAY",
        "trainer": "NİHAT YILDIRIM",
        "weight": 56,
        "odds": 14.9,
        "finishTime": "1.34.64",
        "age": 4
      },
      {
        "position": 7,
        "no": "5",
        "name": "TELVE",
        "jockey": "HALİL POLAT",
        "trainer": "KENAN KORKMAZ",
        "weight": 58,
        "odds": 13.6,
        "finishTime": "1.35.17",
        "age": 4
      },
      {
        "position": 8,
        "no": "3",
        "name": "RED LINE",
        "jockey": "ERHAN YAVUZ",
        "trainer": "ZAFER TEMUÇİN",
        "weight": 58,
        "odds": 7.15,
        "finishTime": "1.36.93",
        "age": 4
      },
      {
        "position": 9,
        "no": "7",
        "name": "SEVDA KARASI",
        "jockey": "ROBİN BORAN DÜNDAR",
        "trainer": "DENİZ ALTIN",
        "weight": 52,
        "odds": 60.35,
        "finishTime": "1.47.47",
        "age": 4
      }
    ]
  },
  {
    "date": "2025-04-04",
    "raceNo": 1,
    "venue": "Gulfstream Park ABD",
    "distance": 0,
    "surface": "",
    "raceClass": "Tapeta",
    "horses": [
      {
        "position": 1,
        "no": "3",
        "name": "SHELOVESTOTRAVEL",
        "jockey": "MIGUEL ANGEL VASQUEZ",
        "trainer": "JOSE FRANCISCO D'ANGELO",
        "weight": 53.5,
        "odds": 3.7,
        "finishTime": "1.03.27",
        "age": 3
      },
      {
        "position": 2,
        "no": "1",
        "name": "MAJESTY'S SONG",
        "jockey": "EDWIN GONZALEZ",
        "trainer": "MARK E. CASSE",
        "weight": 56.5,
        "odds": 3.5,
        "finishTime": "",
        "age": 4
      },
      {
        "position": 3,
        "no": "5",
        "name": "CITY MINUTE",
        "jockey": "MICAH J. HUSBANDS",
        "trainer": "SAFFIE A. JOSEPH, JR.",
        "weight": 53.5,
        "odds": 1.95,
        "finishTime": "",
        "age": 4
      },
      {
        "position": 4,
        "no": "2",
        "name": "LA CYBER",
        "jockey": "EDGAR PEREZ",
        "trainer": "JOSE FRANCISCO D'ANGELO",
        "weight": 53.5,
        "odds": 18.7,
        "finishTime": "",
        "age": 3
      },
      {
        "position": 5,
        "no": "7",
        "name": "MARIO'S SWEET GIRL",
        "jockey": "JOSE E. MORELOS",
        "trainer": "STEVE BUDHOO",
        "weight": 56.5,
        "odds": 13.05,
        "finishTime": "",
        "age": 5
      },
      {
        "position": 6,
        "no": "4",
        "name": "ELLAGIO",
        "jockey": "PACO LOPEZ",
        "trainer": "STEVE KLESARIS",
        "weight": 56.5,
        "odds": 6.9,
        "finishTime": "",
        "age": 4
      }
    ]
  },
  {
    "date": "2025-04-04",
    "raceNo": 2,
    "venue": "Gulfstream Park ABD",
    "distance": 1600,
    "surface": "Çim",
    "raceClass": "",
    "horses": [
      {
        "position": 1,
        "no": "8",
        "name": "ALASDAIR",
        "jockey": "PACO LOPEZ",
        "trainer": "NOLAN RAMSEY",
        "weight": 55.5,
        "odds": 2.1,
        "finishTime": "1.34.83",
        "age": 6
      },
      {
        "position": 2,
        "no": "4",
        "name": "FLAT TOP BOX",
        "jockey": "MIGUEL ANGEL VASQUEZ",
        "trainer": "RONALD B. SPATZ",
        "weight": 55.5,
        "odds": 9.15,
        "finishTime": "",
        "age": 5
      },
      {
        "position": 3,
        "no": "5",
        "name": "REMERTON",
        "jockey": "EDWIN GONZALEZ",
        "trainer": "SCOTT D. ACKER",
        "weight": 55.5,
        "odds": 10.15,
        "finishTime": "",
        "age": 4
      },
      {
        "position": 4,
        "no": "6",
        "name": "ORTUS",
        "jockey": "JORGE RUIZ",
        "trainer": "CHRISTOPHE CLEMENT",
        "weight": 55.5,
        "odds": 9.2,
        "finishTime": "",
        "age": 6
      },
      {
        "position": 5,
        "no": "7",
        "name": "BREAKWATER",
        "jockey": "EDGARD J. ZAYAS",
        "trainer": "MICHAEL J. MAKER",
        "weight": 55.5,
        "odds": 8.2,
        "finishTime": "",
        "age": 6
      },
      {
        "position": 6,
        "no": "2",
        "name": "PALACE VIEW",
        "jockey": "JOE BRAVO",
        "trainer": "MARK E. CASSE",
        "weight": 55.5,
        "odds": 4.05,
        "finishTime": "",
        "age": 5
      },
      {
        "position": 7,
        "no": "3",
        "name": "HUSBAND MATERIAL",
        "jockey": "LEONEL REYES",
        "trainer": "FERNANDO ABREU",
        "weight": 55.5,
        "odds": 15.8,
        "finishTime": "",
        "age": 6
      },
      {
        "position": 8,
        "no": "9",
        "name": "JERRY'S TURN",
        "jockey": "RAJIV MARAGH",
        "trainer": "TIMOTHY A. HILLS",
        "weight": 55.5,
        "odds": 16.9,
        "finishTime": "",
        "age": 7
      },
      {
        "position": 9,
        "no": "1",
        "name": "T B TWELVE ALWAYS",
        "jockey": "MIA NICHOLLS",
        "trainer": "WILLOUGHBY SIMPSON",
        "weight": 52,
        "odds": 16.8,
        "finishTime": "",
        "age": 4
      }
    ]
  },
  {
    "date": "2025-04-04",
    "raceNo": 3,
    "venue": "Gulfstream Park ABD",
    "distance": 1600,
    "surface": "Kum",
    "raceClass": "",
    "horses": [
      {
        "position": 1,
        "no": "6",
        "name": "EASIER SAID",
        "jockey": "MIGUEL ANGEL VASQUEZ",
        "trainer": "TODD A. PLETCHER",
        "weight": 53.5,
        "odds": 2.6,
        "finishTime": "1.40.01",
        "age": 3
      },
      {
        "position": 2,
        "no": "1",
        "name": "SKULL HONOR",
        "jockey": "EDWIN GONZALEZ",
        "trainer": "JOSE FRANCISCO D'ANGELO",
        "weight": 53.5,
        "odds": 1.45,
        "finishTime": "",
        "age": 3
      },
      {
        "position": 3,
        "no": "2",
        "name": "THEO'S THUNDER",
        "jockey": "RENZO ROJAS",
        "trainer": "ANTONIO SANO",
        "weight": 53.5,
        "odds": 15.1,
        "finishTime": "",
        "age": 3
      },
      {
        "position": 4,
        "no": "3",
        "name": "HANDSOME FOX",
        "jockey": "LEONEL REYES",
        "trainer": "GERALD JAMES",
        "weight": 53.5,
        "odds": 30.25,
        "finishTime": "",
        "age": 3
      },
      {
        "position": 5,
        "no": "4",
        "name": "BRIGHT LIGHTS JOE",
        "jockey": "EDGARD J. ZAYAS",
        "trainer": "BRENDAN P. WALSH",
        "weight": 53.5,
        "odds": 11.4,
        "finishTime": "",
        "age": 3
      },
      {
        "position": 6,
        "no": "5",
        "name": "KHARIF",
        "jockey": "YOLBER TORRES",
        "trainer": "JAVIER E. GONZALEZ",
        "weight": 49,
        "odds": 33.7,
        "finishTime": "",
        "age": 3
      },
      {
        "position": 7,
        "no": "7",
        "name": "JOHN'S IN CHARGE",
        "jockey": "JORGE RUIZ",
        "trainer": "JEREMIAH O'DWYER",
        "weight": 53.5,
        "odds": 20.5,
        "finishTime": "",
        "age": 3
      }
    ]
  },
  {
    "date": "2025-04-04",
    "raceNo": 4,
    "venue": "Gulfstream Park ABD",
    "distance": 0,
    "surface": "",
    "raceClass": "Tapeta",
    "horses": [
      {
        "position": 1,
        "no": "4",
        "name": "TORCH IS PASSED",
        "jockey": "MIGUEL ANGEL VASQUEZ",
        "trainer": "NOLAN RAMSEY",
        "weight": 54.5,
        "odds": 3.35,
        "finishTime": "1.03.41",
        "age": 3
      },
      {
        "position": 2,
        "no": "5",
        "name": "LAZIO",
        "jockey": "EDGARD J. ZAYAS",
        "trainer": "MARY LIGHTNER",
        "weight": 54.5,
        "odds": 5.1,
        "finishTime": "",
        "age": 3
      },
      {
        "position": 3,
        "no": "3",
        "name": "CARCONE",
        "jockey": "SHAUN BRIDGMOHAN",
        "trainer": "MELANIE GIDDINGS",
        "weight": 54.5,
        "odds": 2.45,
        "finishTime": "",
        "age": 3
      },
      {
        "position": 4,
        "no": "6",
        "name": "TO MONARCH",
        "jockey": "PACO LOPEZ",
        "trainer": "DAVID FAWKES",
        "weight": 53.5,
        "odds": 3.4,
        "finishTime": "",
        "age": 3
      },
      {
        "position": 5,
        "no": "1",
        "name": "NOSTALGIA'S SMILE",
        "jockey": "RAJIV MARAGH",
        "trainer": "CARLOS A. DAVID",
        "weight": 53.5,
        "odds": 11.15,
        "finishTime": "",
        "age": 3
      },
      {
        "position": 6,
        "no": "2",
        "name": "BUCCHERO'S DUDE",
        "jockey": "RENZO ROJAS",
        "trainer": "MICHAEL YATES",
        "weight": 53.5,
        "odds": 18.1,
        "finishTime": "",
        "age": 3
      }
    ]
  },
  {
    "date": "2025-04-04",
    "raceNo": 5,
    "venue": "Gulfstream Park ABD",
    "distance": 1000,
    "surface": "Çim",
    "raceClass": "",
    "horses": [
      {
        "position": 1,
        "no": "8",
        "name": "LIONZA",
        "jockey": "EDGAR PEREZ",
        "trainer": "GUSTAVO DELGADO",
        "weight": 55.5,
        "odds": 0,
        "finishTime": "0.55.44",
        "age": 4
      },
      {
        "position": 2,
        "no": "3",
        "name": "LAILA BELLA GIRL",
        "jockey": "EDGARD J. ZAYAS",
        "trainer": "J. DAVID BRADDY",
        "weight": 55.5,
        "odds": 0,
        "finishTime": "",
        "age": 4
      },
      {
        "position": 3,
        "no": "6",
        "name": "SPERANZOSA",
        "jockey": "PACO LOPEZ",
        "trainer": "CHRISTOPHE CLEMENT",
        "weight": 55.5,
        "odds": 0,
        "finishTime": "",
        "age": 4
      },
      {
        "position": 4,
        "no": "4",
        "name": "ALAS DORADAS",
        "jockey": "MIGUEL ANGEL VASQUEZ",
        "trainer": "JOSE HERNANDEZ AGREDA",
        "weight": 55.5,
        "odds": 0,
        "finishTime": "",
        "age": 4
      },
      {
        "position": 5,
        "no": "2",
        "name": "CHEECA BLUE",
        "jockey": "EDWIN GONZALEZ",
        "trainer": "JOSE FRANCISCO D'ANGELO",
        "weight": 55.5,
        "odds": 0,
        "finishTime": "",
        "age": 4
      },
      {
        "position": 6,
        "no": "7",
        "name": "FIERY",
        "jockey": "RAJIV MARAGH",
        "trainer": "JOSEPH C. CATANESE III",
        "weight": 55.5,
        "odds": 0,
        "finishTime": "",
        "age": 4
      },
      {
        "position": 7,
        "no": "1",
        "name": "GIRVIN STAR",
        "jockey": "JONATHAN OCASIO",
        "trainer": "EDUARDO NUNEZ",
        "weight": 55.5,
        "odds": 0,
        "finishTime": "",
        "age": 4
      },
      {
        "position": 8,
        "no": "5",
        "name": "MOLLY'S A BULLET",
        "jockey": "JORGE RUIZ",
        "trainer": "ANTHONY R. MARGOTTA, JR.",
        "weight": 55.5,
        "odds": 0,
        "finishTime": "",
        "age": 4
      }
    ]
  },
  {
    "date": "2025-04-04",
    "raceNo": 6,
    "venue": "Gulfstream Park ABD",
    "distance": 1200,
    "surface": "Kum",
    "raceClass": "",
    "horses": [
      {
        "position": 1,
        "no": "7",
        "name": "ARROGANCY",
        "jockey": "EDWIN GONZALEZ",
        "trainer": "JOSE FRANCISCO D'ANGELO",
        "weight": 55.5,
        "odds": 1.25,
        "finishTime": "1.10.56",
        "age": 4
      },
      {
        "position": 2,
        "no": "2",
        "name": "COLDSTREAM",
        "jockey": "EDGARD J. ZAYAS",
        "trainer": "SAFFIE A. JOSEPH, JR.",
        "weight": 55.5,
        "odds": 2.15,
        "finishTime": "",
        "age": 5
      },
      {
        "position": 3,
        "no": "3",
        "name": "PRACTIKO",
        "jockey": "MIGUEL ANGEL VASQUEZ",
        "trainer": "JOSE FRANCISCO D'ANGELO",
        "weight": 55.5,
        "odds": 1.25,
        "finishTime": "",
        "age": 5
      },
      {
        "position": 4,
        "no": "1",
        "name": "DANZIG CHIPS",
        "jockey": "JORGE RUIZ",
        "trainer": "RONALD B. SPATZ",
        "weight": 55.5,
        "odds": 9.4,
        "finishTime": "",
        "age": 5
      }
    ]
  },
  {
    "date": "2025-04-04",
    "raceNo": 7,
    "venue": "Gulfstream Park ABD",
    "distance": 0,
    "surface": "",
    "raceClass": "Tapeta",
    "horses": [
      {
        "position": 1,
        "no": "1",
        "name": "MS. TART",
        "jockey": "LEONEL REYES",
        "trainer": "KEVIN RICE",
        "weight": 55.5,
        "odds": 0,
        "finishTime": "1.03.42",
        "age": 4
      },
      {
        "position": 2,
        "no": "2",
        "name": "TIME PASSAGE",
        "jockey": "PACO LOPEZ",
        "trainer": "EDWARD PLESA, JR.",
        "weight": 54.5,
        "odds": 0,
        "finishTime": "",
        "age": 5
      },
      {
        "position": 3,
        "no": "5",
        "name": "TRUMPETS",
        "jockey": "EDGAR PEREZ",
        "trainer": "JOSEPH C. CATANESE III",
        "weight": 54.5,
        "odds": 0,
        "finishTime": "",
        "age": 4
      },
      {
        "position": 4,
        "no": "6",
        "name": "OH DARLIN",
        "jockey": "EDWIN GONZALEZ",
        "trainer": "HAPPY ALTER",
        "weight": 54.5,
        "odds": 0,
        "finishTime": "",
        "age": 5
      },
      {
        "position": 5,
        "no": "3",
        "name": "SIMPLY STATED",
        "jockey": "JORGE RUIZ",
        "trainer": "MICHAEL J. TROMBETTA",
        "weight": 54.5,
        "odds": 0,
        "finishTime": "",
        "age": 5
      },
      {
        "position": 6,
        "no": "4",
        "name": "ETRURIAN",
        "jockey": "EDGARD J. ZAYAS",
        "trainer": "JOSEPH F. ORSENO",
        "weight": 54.5,
        "odds": 0,
        "finishTime": "",
        "age": 4
      }
    ]
  },
  {
    "date": "2025-04-04",
    "raceNo": 8,
    "venue": "Gulfstream Park ABD",
    "distance": 1400,
    "surface": "Kum",
    "raceClass": "",
    "horses": [
      {
        "position": 1,
        "no": "6",
        "name": "EMIRATES AFFAIR",
        "jockey": "PACO LOPEZ",
        "trainer": "J. KENT SWEEZEY",
        "weight": 55.5,
        "odds": 1.55,
        "finishTime": "1.24.33",
        "age": 7
      },
      {
        "position": 2,
        "no": "2",
        "name": "ATALANTA ALEXANDRA",
        "jockey": "YOLBER TORRES",
        "trainer": "GEORGINA BAXTER",
        "weight": 50,
        "odds": 14.1,
        "finishTime": "",
        "age": 5
      },
      {
        "position": 3,
        "no": "7",
        "name": "ALESS QUEEN",
        "jockey": "EDGAR PEREZ",
        "trainer": "JOSE FRANCISCO D'ANGELO",
        "weight": 54.5,
        "odds": 3.15,
        "finishTime": "",
        "age": 4
      },
      {
        "position": 4,
        "no": "5",
        "name": "GULLFAXI",
        "jockey": "JORGE RUIZ",
        "trainer": "CARLOS A. DAVID",
        "weight": 54.5,
        "odds": 14,
        "finishTime": "",
        "age": 4
      },
      {
        "position": 5,
        "no": "4",
        "name": "NEOM CITY",
        "jockey": "JOSE E. MORELOS",
        "trainer": "TAREQ MOUBARAK",
        "weight": 54.5,
        "odds": 6.2,
        "finishTime": "",
        "age": 4
      },
      {
        "position": 6,
        "no": "1",
        "name": "FONTINA",
        "jockey": "MICAH J. HUSBANDS",
        "trainer": "RONALD B. SPATZ",
        "weight": 51.5,
        "odds": 12.15,
        "finishTime": "",
        "age": 4
      }
    ]
  },
  {
    "date": "2025-04-04",
    "raceNo": 9,
    "venue": "Gulfstream Park ABD",
    "distance": 1600,
    "surface": "Çim",
    "raceClass": "",
    "horses": [
      {
        "position": 1,
        "no": "3",
        "name": "QUIZLER",
        "jockey": "PACO LOPEZ",
        "trainer": "KELLY J. BREEN",
        "weight": 54.5,
        "odds": 1.9,
        "finishTime": "1.34.60",
        "age": 3
      },
      {
        "position": 2,
        "no": "4",
        "name": "BACKDOOR ROYALTY",
        "jockey": "RAJIV MARAGH",
        "trainer": "J. KENT SWEEZEY",
        "weight": 53.5,
        "odds": 8.15,
        "finishTime": "",
        "age": 3
      },
      {
        "position": 3,
        "no": "5",
        "name": "DUAL INCOME",
        "jockey": "EDGARD J. ZAYAS",
        "trainer": "JOSEPH F. ORSENO",
        "weight": 53.5,
        "odds": 3.75,
        "finishTime": "",
        "age": 3
      },
      {
        "position": 4,
        "no": "1",
        "name": "ESPERANZITO",
        "jockey": "EDWIN GONZALEZ",
        "trainer": "CARLOS LUIS PEREZ",
        "weight": 53.5,
        "odds": 4.95,
        "finishTime": "",
        "age": 3
      },
      {
        "position": 5,
        "no": "6",
        "name": "RIVER OF TIME",
        "jockey": "MIGUEL ANGEL VASQUEZ",
        "trainer": "WILLIAM THARRENOS",
        "weight": 53.5,
        "odds": 9.15,
        "finishTime": "",
        "age": 3
      },
      {
        "position": 6,
        "no": "8",
        "name": "MY BOY ROCKY",
        "jockey": "JOSE E. MORELOS",
        "trainer": "JORGE DELGADO",
        "weight": 53.5,
        "odds": 18.35,
        "finishTime": "",
        "age": 3
      },
      {
        "position": 7,
        "no": "2",
        "name": "FRIOLENTO",
        "jockey": "LEONEL REYES",
        "trainer": "NICHOLAS PALMER",
        "weight": 53.5,
        "odds": 15.7,
        "finishTime": "",
        "age": 3
      }
    ]
  },
  {
    "date": "2025-04-04",
    "raceNo": 1,
    "venue": "Bath Birleşik Krallık",
    "distance": 2800,
    "surface": "Çim",
    "raceClass": "",
    "horses": [
      {
        "position": 1,
        "no": "5",
        "name": "MAN OF THE SEA (IRE)",
        "jockey": "D PROBERT",
        "trainer": "N MULHOLLAND",
        "weight": 57.5,
        "odds": 8.65,
        "finishTime": "",
        "age": 9
      },
      {
        "position": 3,
        "no": "6",
        "name": "CORNISH STORM",
        "jockey": "R HORNBY",
        "trainer": "W KITTOW",
        "weight": 57.5,
        "odds": 2.15,
        "finishTime": "",
        "age": 6
      },
      {
        "position": 5,
        "no": "1",
        "name": "FAIR DINKUM (IRE)",
        "jockey": "TARYN LANGLEY",
        "trainer": "J SCOTT",
        "weight": 58.5,
        "odds": 12.5,
        "finishTime": "",
        "age": 5
      },
      {
        "position": 7,
        "no": "4",
        "name": "SPITFIRE BRIDGE",
        "jockey": "C BİSHOP",
        "trainer": "MİSS S WEST",
        "weight": 58,
        "odds": 10,
        "finishTime": "",
        "age": 5
      }
    ]
  },
  {
    "date": "2025-04-04",
    "raceNo": 3,
    "venue": "Bath Birleşik Krallık",
    "distance": 1000,
    "surface": "Çim",
    "raceClass": "",
    "horses": [
      {
        "position": 1,
        "no": "7",
        "name": "TOURIST",
        "jockey": "S M LEVEY",
        "trainer": "R COWELL",
        "weight": 59,
        "odds": 2.85,
        "finishTime": "",
        "age": 4
      },
      {
        "position": 2,
        "no": "1",
        "name": "PEPSI CAT (IRE)",
        "jockey": "D COSTELLO",
        "trainer": "STEPH HOLLINSHEAD",
        "weight": 62,
        "odds": 6.25,
        "finishTime": "",
        "age": 6
      },
      {
        "position": 3,
        "no": "2",
        "name": "GRACE ANGEL",
        "jockey": "JASON WATSON",
        "trainer": "DARRYLL HOLLAND",
        "weight": 61.5,
        "odds": 13.6,
        "finishTime": "",
        "age": 5
      },
      {
        "position": 4,
        "no": "3",
        "name": "REGAL ENVOY (IRE)",
        "jockey": "BRANDON WILKIE",
        "trainer": "W KNIGHT",
        "weight": 59,
        "odds": 4.6,
        "finishTime": "",
        "age": 6
      },
      {
        "position": 5,
        "no": "9",
        "name": "SO SMART (IRE)",
        "jockey": "T HEARD",
        "trainer": "G HARRIS",
        "weight": 53,
        "odds": 42,
        "finishTime": "",
        "age": 6
      },
      {
        "position": 6,
        "no": "4",
        "name": "MISS SHOW OFF",
        "jockey": "D PROBERT",
        "trainer": "C COX",
        "weight": 59.5,
        "odds": 8.5,
        "finishTime": "",
        "age": 4
      },
      {
        "position": 7,
        "no": "8",
        "name": "CONNIE'S ROSE",
        "jockey": "F MARSH",
        "trainer": "G HARRIS",
        "weight": 55.5,
        "odds": 12.5,
        "finishTime": "",
        "age": 6
      },
      {
        "position": 8,
        "no": "6",
        "name": "POP STAR (IRE)",
        "jockey": "K O'NEILL",
        "trainer": "ALICE HAYNES",
        "weight": 59,
        "odds": 5.75,
        "finishTime": "",
        "age": 5
      },
      {
        "position": 9,
        "no": "5",
        "name": "JACQUELINA (IRE)",
        "jockey": "GRACE MCENTEE",
        "trainer": "P MCENTEE",
        "weight": 59,
        "odds": 7.1,
        "finishTime": "",
        "age": 6
      }
    ]
  },
  {
    "date": "2025-04-04",
    "raceNo": 4,
    "venue": "Bath Birleşik Krallık",
    "distance": 1160,
    "surface": "Çim",
    "raceClass": "",
    "horses": [
      {
        "position": 2,
        "no": "3",
        "name": "ROYAL ACCORD",
        "jockey": "S M LEVEY",
        "trainer": "S C WİLLİAMS",
        "weight": 60.5,
        "odds": 2.45,
        "finishTime": "",
        "age": 3
      }
    ]
  },
  {
    "date": "2025-04-04",
    "raceNo": 5,
    "venue": "Bath Birleşik Krallık",
    "distance": 1600,
    "surface": "Çim",
    "raceClass": "",
    "horses": [
      {
        "position": 2,
        "no": "5",
        "name": "HIGH ON HOPE",
        "jockey": "P-L JAMİN",
        "trainer": "T DASCOMBE",
        "weight": 57.5,
        "odds": 4.45,
        "finishTime": "",
        "age": 3
      }
    ]
  },
  {
    "date": "2025-04-04",
    "raceNo": 6,
    "venue": "Bath Birleşik Krallık",
    "distance": 1600,
    "surface": "Çim",
    "raceClass": "",
    "horses": [
      {
        "position": 1,
        "no": "2",
        "name": "DARVEL (IRE)",
        "jockey": "D PROBERT",
        "trainer": "P CHAMİNGS",
        "weight": 61.5,
        "odds": 8.7,
        "finishTime": "",
        "age": 7
      },
      {
        "position": 2,
        "no": "6",
        "name": "SOI DAO (IRE)",
        "jockey": "F MARSH",
        "trainer": "A WİNTLE",
        "weight": 60.5,
        "odds": 3,
        "finishTime": "",
        "age": 6
      },
      {
        "position": 3,
        "no": "1",
        "name": "KING OF SPEED (IRE)",
        "jockey": "J PEATE",
        "trainer": "M LOUGHNANE",
        "weight": 61.5,
        "odds": 6.3,
        "finishTime": "",
        "age": 6
      },
      {
        "position": 4,
        "no": "4",
        "name": "MY AMBITION (IRE)",
        "jockey": "R HORNBY",
        "trainer": "D COAKLEY",
        "weight": 61,
        "odds": 15.55,
        "finishTime": "",
        "age": 6
      },
      {
        "position": 5,
        "no": "3",
        "name": "THAT'S FOR SURE (IRE)",
        "jockey": "P-L JAMİN",
        "trainer": "MİCHAEL KEADY",
        "weight": 61.5,
        "odds": 15.8,
        "finishTime": "",
        "age": 4
      },
      {
        "position": 6,
        "no": "10",
        "name": "BAYNOONA (IRE)",
        "jockey": "R CLUTTERBUCK",
        "trainer": "MRS S GARDNER",
        "weight": 58,
        "odds": 23,
        "finishTime": "",
        "age": 4
      },
      {
        "position": 7,
        "no": "5",
        "name": "OUTRACE (IRE)",
        "jockey": "TYRESE CAMERON",
        "trainer": "R HANNON",
        "weight": 58,
        "odds": 15.95,
        "finishTime": "",
        "age": 5
      },
      {
        "position": 8,
        "no": "11",
        "name": "VILLALOBOS (IRE)",
        "jockey": "A FARRAGHER",
        "trainer": "S HODGSON",
        "weight": 57.5,
        "odds": 13.05,
        "finishTime": "",
        "age": 6
      },
      {
        "position": 11,
        "no": "8",
        "name": "MONKS MEAD",
        "jockey": "G BASS",
        "trainer": "M USHER",
        "weight": 57.5,
        "odds": 14.7,
        "finishTime": "",
        "age": 4
      },
      {
        "position": 12,
        "no": "12",
        "name": "TOO MUCH TREVOR",
        "jockey": "K O'NEİLL",
        "trainer": "G HARRİS",
        "weight": 57.5,
        "odds": 21,
        "finishTime": "",
        "age": 4
      }
    ]
  },
  {
    "date": "2025-04-04",
    "raceNo": 7,
    "venue": "Bath Birleşik Krallık",
    "distance": 2340,
    "surface": "Çim",
    "raceClass": "",
    "horses": [
      {
        "position": 1,
        "no": "7",
        "name": "JIMMY MARK (IRE)",
        "jockey": "K O'NEİLL",
        "trainer": "W KİTTOW",
        "weight": 55.5,
        "odds": 8.9,
        "finishTime": "",
        "age": 5
      },
      {
        "position": 2,
        "no": "2",
        "name": "WATERLOO SUNSET",
        "jockey": "T HEARD",
        "trainer": "D COAKLEY",
        "weight": 61,
        "odds": 5.2,
        "finishTime": "",
        "age": 7
      },
      {
        "position": 3,
        "no": "8",
        "name": "LADYPACKSAPUNCH",
        "jockey": "S HITCHCOTT",
        "trainer": "G HARRIS",
        "weight": 53,
        "odds": 3.25,
        "finishTime": "",
        "age": 6
      },
      {
        "position": 4,
        "no": "1",
        "name": "PALAZZO PERSICO (IRE)",
        "jockey": "A FARRAGHER",
        "trainer": "E DUNLOP",
        "weight": 61.5,
        "odds": 13.4,
        "finishTime": "",
        "age": 4
      },
      {
        "position": 5,
        "no": "3",
        "name": "MEET ME IN MERAKI",
        "jockey": "JORDAN WILLIAMS",
        "trainer": "P EVANS",
        "weight": 58.5,
        "odds": 7.45,
        "finishTime": "",
        "age": 4
      },
      {
        "position": 6,
        "no": "4",
        "name": "STARFIGHTER",
        "jockey": "D PROBERT",
        "trainer": "M LOUGHNANE",
        "weight": 58,
        "odds": 6.7,
        "finishTime": "",
        "age": 9
      },
      {
        "position": 7,
        "no": "5",
        "name": "MREMBO",
        "jockey": "R HORNBY",
        "trainer": "J PORTMAN",
        "weight": 56.5,
        "odds": 2.95,
        "finishTime": "",
        "age": 6
      },
      {
        "position": 8,
        "no": "6",
        "name": "BAIKAL",
        "jockey": "F MARSH",
        "trainer": "G HARRIS",
        "weight": 56.5,
        "odds": 3.25,
        "finishTime": "",
        "age": 6
      }
    ]
  }
]